odoo/addons/avoid_exception_activity_notification/README.rst
odoo/addons/avoid_exception_activity_notification/__init__.py
odoo/addons/avoid_exception_activity_notification/__manifest__.py
odoo/addons/avoid_exception_activity_notification/models/__init__.py
odoo/addons/avoid_exception_activity_notification/models/mail_activity.py
odoo/addons/avoid_exception_activity_notification/static/description/icon.png
odoo14_addon_avoid_exception_activity_notification-14.0.1.0.0.dist-info/METADATA
odoo14_addon_avoid_exception_activity_notification-14.0.1.0.0.dist-info/WHEEL
odoo14_addon_avoid_exception_activity_notification-14.0.1.0.0.dist-info/top_level.txt
odoo14_addon_avoid_exception_activity_notification-14.0.1.0.0.dist-info/RECORD
